huggingface_nas/__init__.py
huggingface_nas/hf_to_nas.py
huggingface_nas/load.py
huggingface_nas/local_to_nas.py
huggingface_nas/webapi.py
huggingface_nas-0.1.1.dist-info/LICENSE
huggingface_nas-0.1.1.dist-info/METADATA
huggingface_nas-0.1.1.dist-info/WHEEL
huggingface_nas-0.1.1.dist-info/top_level.txt
huggingface_nas-0.1.1.dist-info/RECORD
