Metadata-Version: 2.1
Name: huggingface-nas
Version: 0.1.1
Summary: Using NAS such as huggingface hub
Home-page: https://github.com/tony9402/huggingface-NAS
Author: tony9402
Author-email: tony9402@naver.com
License: Apache 2.0 License
Keywords: huggingface nas synology
Platform: UNKNOWN
Classifier: Intended Audience :: Developers
Classifier: Intended Audience :: Education
Classifier: Intended Audience :: Science/Research
Classifier: License :: OSI Approved :: Apache Software License
Classifier: Operating System :: OS Independent
Classifier: Programming Language :: Python :: 3
Classifier: Programming Language :: Python :: 3.8
Classifier: Programming Language :: Python :: 3.9
Classifier: Programming Language :: Python :: 3.10
Classifier: Programming Language :: Python :: 3.11
Classifier: Programming Language :: Python :: 3.12
Classifier: Programming Language :: Python :: 3.13
Requires-Python: >=3.8.0
License-File: LICENSE
Requires-Dist: tqdm>=4.27
Requires-Dist: datasets>=3.1.0
Requires-Dist: requests
Requires-Dist: synology-api>=0.7.3
